setup.py
texty/__init__.py
texty/tag.py
texty/tok.py
texty/txt.py
texty.egg-info/PKG-INFO
texty.egg-info/SOURCES.txt
texty.egg-info/dependency_links.txt
texty.egg-info/top_level.txt