Metadata-Version: 1.1
Name: texty
Version: 0.0.5
Summary: Utility & wrapper functions for text processing and linguistics.
Home-page: https://github.com/magnusnissel/texty
Author: Magnus Nissel
Author-email: magnus@nissel.org
License: GPL
Keywords: text,nlproc,nlp,linguistics,digital humanities
Platform: UNKNOWN
Classifier: Development Status :: 3 - Alpha
Classifier: Programming Language :: Python
Classifier: Programming Language :: Python :: 3
